pyrimls/__init__.py
pyrimls/main.py
pyrimls/reconstructor.py
pyrimls-0.0.1.dist-info/METADATA
pyrimls-0.0.1.dist-info/WHEEL
pyrimls-0.0.1.dist-info/RECORD
